PyTaskbar/ProgressAPI.py
PyTaskbar/__init__.py
pytaskbar-0.1.0.dist-info/licenses/LICENSE
pytaskbar-0.1.0.dist-info/METADATA
pytaskbar-0.1.0.dist-info/WHEEL
pytaskbar-0.1.0.dist-info/top_level.txt
pytaskbar-0.1.0.dist-info/RECORD
