Metadata-Version: 2.4
Name: PyTaskbar
Version: 0.1.0
Summary: The ultimate taskbar progress python package!
Home-page: https://github.com/N3RDIUM/PyTaskbar
Author: N3RDIUM
Classifier: License :: OSI Approved :: MIT License
Classifier: Operating System :: Microsoft :: Windows :: Windows 10
Requires-Python: >=3.6
License-File: LICENSE
Requires-Dist: comtypes
Requires-Dist: pygetwindow
Requires-Dist: setuptools
Dynamic: author
Dynamic: classifier
Dynamic: description
Dynamic: description-content-type
Dynamic: home-page
Dynamic: license-file
Dynamic: requires-dist
Dynamic: requires-python
Dynamic: summary
